nbappinator/__init__.py
nbappinator/_version.py
nbappinator/aggridhelper.py
nbappinator/appinator.py
nbappinator/browser_title.py
nbappinator/datagrid.py
nbappinator/jinjamagic.py
nbappinator/plotly_charts.py
nbappinator/treew.py
nbappinator-0.1.9.dist-info/LICENSE.md
nbappinator-0.1.9.dist-info/METADATA
nbappinator-0.1.9.dist-info/WHEEL
nbappinator-0.1.9.dist-info/RECORD
