Metadata-Version: 2.1
Name: nbappinator
Version: 0.1.9
Summary: Jupyter Notebook Application Builder
Home-page: https://github.com/iqmo-org/nbappinator
License: BSD-3-Clause
Keywords: nbappinator,Jupyter,Bquant
Author: Paul T
Author-email: paul@iqmo.com
Maintainer: Paul T
Maintainer-email: paul@iqmo.com
Requires-Python: >=3.11,<4.0
Classifier: License :: OSI Approved :: BSD License
Classifier: Programming Language :: Python :: 3
Classifier: Programming Language :: Python :: 3.11
Classifier: Programming Language :: Python :: 3.12
Requires-Dist: ipyaggrid (>=0.5.4,<0.6.0)
Requires-Dist: ipytree (>=0.2.2,<0.3.0)
Requires-Dist: ipyvuetify (>=1.9.4,<2.0.0)
Requires-Dist: ipywidgets (>=8.1.3,<9.0.0)
Requires-Dist: pandas (>=2.2.2,<3.0.0)
Requires-Dist: plotly (>=5.22.0,<6.0.0)
Project-URL: Repository, https://github.com/iqmo-org/nbappinator
